rwrapr/__init__.py
rwrapr/convert_py2r.py
rwrapr/convert_r2py.py
rwrapr/lazy_rexpr.py
rwrapr/library.py
rwrapr/load_namespace.py
rwrapr/nputils.py
rwrapr/py.typed
rwrapr/rarray.py
rwrapr/rattributes.py
rwrapr/rdataframe.py
rwrapr/renv.py
rwrapr/rfactor.py
rwrapr/rfunction.py
rwrapr/rlist.py
rwrapr/rutils.py
rwrapr/rview.py
rwrapr/settings.py
rwrapr/sparse.py
rwrapr/toggle_rview.py
rwrapr/utils.py
rwrapr-0.9.3.dist-info/METADATA
rwrapr-0.9.3.dist-info/WHEEL
rwrapr-0.9.3.dist-info/licenses/LICENSE
rwrapr-0.9.3.dist-info/RECORD
