Metadata-Version: 2.4
Name: rwrapr
Version: 0.9.3
Summary: Python package for using R in Python
License: MIT
License-File: LICENSE
Author: Kjell Solem Slupphaug
Author-email: kjell.solem.slupphaug@ssb.no
Requires-Python: >=3.10,<4.0
Classifier: Development Status :: 4 - Beta
Classifier: License :: OSI Approved :: MIT License
Classifier: Programming Language :: Python :: 3
Classifier: Programming Language :: Python :: 3.10
Classifier: Programming Language :: Python :: 3.11
Classifier: Programming Language :: Python :: 3.12
Classifier: Programming Language :: Python :: 3.13
Classifier: Programming Language :: Python :: 3.14
Requires-Dist: dapla-toolbelt (>=1.3.2)
Requires-Dist: jinja2 (>=3.1.5)
Requires-Dist: numpy (>=1.26.4)
Requires-Dist: pandas (>=2.2.0)
Requires-Dist: rpy2 (>=3.5.16)
Requires-Dist: scipy (>=1.3)
Requires-Dist: termcolor (>=2.4.0)
Project-URL: Changelog, https://github.com/statisticsnorway/ssb-rwrapr/releases
Project-URL: Documentation, https://statisticsnorway.github.io/ssb-rwrapr
Project-URL: Homepage, https://github.com/statisticsnorway/ssb-rwrapr
Project-URL: Repository, https://github.com/statisticsnorway/ssb-rwrapr
